ssms/__init__.py
ssms/curve_fit_monopile.py
ssms/load_QLS.py
ssms/data/tower_mass_results.dat
ssms/data/tower_mass_results_extended_depth_results.dat
ssms/models/__init__.py
ssms/models/QLS/10.0_QLS_surrogate_model.pickle
ssms/models/QLS/15.0_QLS_surrogate_model.pickle
ssms/models/QLS/3.4_QLS_surrogate_model.pickle
ssms/tests/__init__.py
ssms/tests/test_QLS.py
ssms-1.0.1.dist-info/LICENSE
ssms-1.0.1.dist-info/METADATA
ssms-1.0.1.dist-info/WHEEL
ssms-1.0.1.dist-info/top_level.txt
ssms-1.0.1.dist-info/zip-safe
ssms-1.0.1.dist-info/RECORD
