Metadata-Version: 2.1
Name: ssms
Version: 1.0.1
Summary: Support structure mass surrogate for offshore wind turbines
Home-page: https://gitlab.windenergy.dtu.dk/TOPFARM/basic-plugins/support-structure-mass-surrogate
Author: DTU Wind Energy
Author-email: mikf@dtu.dk
License: MIT
Project-URL: Documentation, https://topfarm.pages.windenergy.dtu.dk/support-structure-mass-surrogate/
Project-URL: Source, https://gitlab.windenergy.dtu.dk/TOPFARM/basic-plugins/support-structure-mass-surrogate
Project-URL: Tracker, https://gitlab.windenergy.dtu.dk/TOPFARM/basic-plugins/support-structure-mass-surrogate/-/issues
License-File: LICENSE
Requires-Dist: numpy
Requires-Dist: pandas
Requires-Dist: matplotlib
Requires-Dist: scikit-learn
Requires-Dist: openturns
Provides-Extra: docs
Requires-Dist: pypandoc ; extra == 'docs'
Requires-Dist: sphinx ; extra == 'docs'
Requires-Dist: nbsphinx ; extra == 'docs'
Requires-Dist: nbconvert ; extra == 'docs'
Requires-Dist: sphinx-rtd-theme ; extra == 'docs'
Provides-Extra: test
Requires-Dist: pytest ; extra == 'test'
